CHANGES.rst
LICENCE.rst
MANIFEST.in
README.rst
bootstrap-4.3.x.sh
buildout.cfg
nginx.conf.template
setup.py
src/collective/__init__.py
src/collective.azipfele.egg-info/PKG-INFO
src/collective.azipfele.egg-info/SOURCES.txt
src/collective.azipfele.egg-info/dependency_links.txt
src/collective.azipfele.egg-info/entry_points.txt
src/collective.azipfele.egg-info/namespace_packages.txt
src/collective.azipfele.egg-info/not-zip-safe
src/collective.azipfele.egg-info/requires.txt
src/collective.azipfele.egg-info/top_level.txt
src/collective/azipfele/__init__.py
src/collective/azipfele/configure.zcml
src/collective/azipfele/extractors.py
src/collective/azipfele/extractors.rst
src/collective/azipfele/interfaces.py
src/collective/azipfele/settings.py
src/collective/azipfele/setuphandlers.py
src/collective/azipfele/testing.py
src/collective/azipfele/tests.py
src/collective/azipfele/zipper.py
src/collective/azipfele/zipper.rst
src/collective/azipfele/browser/__init__.py
src/collective/azipfele/browser/add.py
src/collective/azipfele/browser/configure.zcml
src/collective/azipfele/browser/download.py
src/collective/azipfele/browser/state.py
src/collective/azipfele/profiles/default/browserlayer.xml
src/collective/azipfele/profiles/default/metadata.xml
src/collective/azipfele/profiles/uninstall/browserlayer.xml
src/collective/azipfele/queue/__init__.py
src/collective/azipfele/queue/configure.zcml
src/collective/azipfele/queue/state.py
src/collective/azipfele/queue/taskqueue/__init__.py
src/collective/azipfele/queue/taskqueue/configure.zcml
src/collective/azipfele/queue/taskqueue/handler.py
src/collective/azipfele/queue/taskqueue/view.py
src/collective/azipfele/queue/zamqp/__init__.py
src/collective/azipfele/queue/zamqp/configure.zcml
src/collective/azipfele/queue/zamqp/taskszamqp.py
src/collective/azipfele/test/__init__.py
src/collective/azipfele/test/robottest_keywords.robot
src/collective/azipfele/test/robottest_variables.py
src/collective/azipfele/test/test.robot
src/collective/azipfele/test/testdata/image1.jpg
src/collective/azipfele/test/testdata/test.txt