Metadata-Version: 2.1
Name: collective.azipfele
Version: 2.0.2
Summary: Creates Zip files from Plone or other content asynchronous
Home-page: https://bluedynamics.com
Author: BlueDynamics Alliance
Author-email: dev@bluedynamics.com
License: GNU General Public Licence
Keywords: async zip plone
Platform: UNKNOWN
Classifier: Development Status :: 5 - Production/Stable
Classifier: Framework :: Plone :: 4.3
Classifier: Framework :: Plone
Classifier: License :: OSI Approved :: GNU General Public License (GPL)
Classifier: Operating System :: OS Independent
Classifier: Programming Language :: Python :: 2.7
Classifier: Programming Language :: Python
Classifier: Topic :: Software Development :: Libraries :: Python Modules
Provides-Extra: test
Provides-Extra: taskqueue
Provides-Extra: zamqp
